[
  {
    "title": "Dog Dad Funny Mug...",
    "price": "$19.95",
    "images": [
      "https://gearbubble-assets.s3.amazonaws.com/5/2849243/20/235/front.png",
      "https://gearbubble-assets.s3.amazonaws.com/5/2849243/20/235/back.png"
    ]
  },
  {
    "title": "To My Son - Love ...",
    "price": "$27.95",
    "images": [
      "https://gearbubble-assets.s3.amazonaws.com/13/476443/52/252/front.png"
    ]
  },
  {
    "title": "DAUGHTER - DAD",
    "price": "$29.95",
    "images": [
      "https://gearbubble-assets.s3.amazonaws.com/13/3658278/37/252/front.png"
    ]
  },
  {
    "title": "I LOVE YOU",
    "price": "$19.95",
    "images": [
      "https://gearbubble-assets.s3.amazonaws.com/5/501056/45/235/front.png",
      "https://gearbubble-assets.s3.amazonaws.com/5/501056/45/235/back.png"
    ]
  },
  {
    "title": "To My Daughter ♥",
    "price": "$34.95",
    "images": [
      "https://gearbubble-assets.s3.amazonaws.com/13/1305643/53/252/front.png"
    ]
  },
  {
    "title": "I Am Mantra Necklace",
    "price": "$29.95",
    "images": [
      "https://gearbubble-assets.s3.amazonaws.com/13/8114/31/252/front.png"
    ]
  },
  {
    "title": "BEST GIFT FOR YOU...",
    "price": "$34.95",
    "images": [
      "https://gearbubble-assets.s3.amazonaws.com/13/438726/52/252/front.png"
    ]
  },
  {
    "title": "To My Gorgeous Wi...",
    "price": "$29.95",
    "images": [
      "https://gearbubble-assets.s3.amazonaws.com/13/485525/53/252/front.png"
    ]
  },
  {
    "title": "❤️ PHOTO TRIBUTE ...",
    "price": "$24.95",
    "images": [
      "https://gearbubble-assets.s3.amazonaws.com/7/289980/22/116/front.png",
      "https://gearbubble-assets.s3.amazonaws.com/7/289980/22/116/back.png"
    ]
  },
  {
    "title": "Dear Cat Dad Mug ...",
    "price": "$19.95",
    "images": [
      "https://gearbubble-assets.s3.amazonaws.com/5/2976915/20/235/front.png",
      "https://gearbubble-assets.s3.amazonaws.com/5/2976915/20/235/back.png"
    ]
  },
  {
    "title": "Daddy's Little Gi...",
    "price": "$39.95",
    "images": [
      "https://gearbubble-assets.s3.amazonaws.com/13/198346/31/252/front.png"
    ]
  },
  {
    "title": "Gilmore Mug Club",
    "price": "$9.95",
    "images": [
      "https://gearbubble-assets.s3.amazonaws.com/5/448443/20/235/front.png",
      "https://gearbubble-assets.s3.amazonaws.com/5/448412/20/235/front.png",
      "https://gearbubble-assets.s3.amazonaws.com/5/444706/20/235/front.png",
      "https://gearbubble-assets.s3.amazonaws.com/5/409453/20/235/front.png",
      "https://gearbubble-assets.s3.amazonaws.com/5/409439/20/235/front.png",
      "https://gearbubble-assets.s3.amazonaws.com/5/453756/20/235/front.png"
    ]
  },
  {
    "title": "I Love You",
    "price": "$19.95",
    "images": [
      "https://gearbubble-assets.s3.amazonaws.com/5/541355/45/235/front.png",
      "https://gearbubble-assets.s3.amazonaws.com/5/541355/45/235/back.png"
    ]
  },
  {
    "title": "The Perfect Gift!",
    "price": "$19.95",
    "images": [
      "https://gearbubble-assets.s3.amazonaws.com/5/578978/45/235/front.png",
      "https://gearbubble-assets.s3.amazonaws.com/5/578978/45/235/back.png"
    ]
  },
  {
    "title": "Personalize - To ...",
    "price": "$24.95",
    "images": [
      "https://gearbubble-assets.s3.amazonaws.com/15/7238451/42/255/front.png"
    ]
  },
  {
    "title": "New - LOVE is Bei...",
    "price": "$19.95",
    "images": [
      "https://gearbubble-assets.s3.amazonaws.com/14/315826/54/252/front.png"
    ]
  },
  {
    "title": "Daughter-in-Law N...",
    "price": "$34.95",
    "images": [
      "https://gearbubble-assets.s3.amazonaws.com/13/3034595/31/252/front.png"
    ]
  },
  {
    "title": "I JUST WANT TO TO...",
    "price": "$19.95",
    "images": [
      "https://gearbubble-assets.s3.amazonaws.com/5/7747652/20/235/front.png",
      "https://gearbubble-assets.s3.amazonaws.com/5/7747652/20/235/back.png"
    ]
  },
  {
    "title": "Dog Dad Mug (pee ...",
    "price": "$19.95",
    "images": [
      "https://gearbubble-assets.s3.amazonaws.com/5/2899880/20/235/front.png",
      "https://gearbubble-assets.s3.amazonaws.com/5/2899880/20/235/back.png"
    ]
  },
  {
    "title": "TO MY WIFE!",
    "price": "$22.95",
    "images": [
      "https://gearbubble-assets.s3.amazonaws.com/5/2479666/20/235/front.png",
      "https://gearbubble-assets.s3.amazonaws.com/5/2479666/20/235/back.png"
    ]
  },
  {
    "title": "LIMITED EDITION ",
    "price": "$27.95",
    "images": [
      "https://gearbubble-assets.s3.amazonaws.com/13/5277677/31/252/front.png"
    ]
  },
  {
    "title": "DAUGHTER - MOM",
    "price": "$29.95",
    "images": [
      "https://gearbubble-assets.s3.amazonaws.com/13/3658361/37/252/front.png"
    ]
  },
  {
    "title": "Dog Mom White Mug",
    "price": "$18.95",
    "images": [
      "https://gearbubble-assets.s3.amazonaws.com/5/3634555/20/235/front.png",
      "https://gearbubble-assets.s3.amazonaws.com/5/3634555/20/235/back.png"
    ]
  },
  {
    "title": "Family Son",
    "price": "$27.95",
    "images": [
      "https://gearbubble-assets.s3.amazonaws.com/13/1073636/31/252/front.png"
    ]
  },
  {
    "title": "In my head I'm Pl...",
    "price": "$24.95",
    "images": [
      "https://gearbubble-assets.s3.amazonaws.com/7/5863554/22/116/front.png",
      "https://gearbubble-assets.s3.amazonaws.com/7/5863554/22/116/back.png"
    ]
  },
  {
    "title": "I Love You More I...",
    "price": "$19.95",
    "images": [
      "https://gearbubble-assets.s3.amazonaws.com/5/7928453/20/235/front.png",
      "https://gearbubble-assets.s3.amazonaws.com/5/7928453/20/235/back.png"
    ]
  },
  {
    "title": "❤️Funny Gift for ...",
    "price": "$22.95",
    "images": [
      "https://gearbubble-assets.s3.amazonaws.com/5/6420063/43/235/front.png",
      "https://gearbubble-assets.s3.amazonaws.com/5/6420063/43/235/back.png"
    ]
  }
]